carrier/__init__.py
carrier/example.py
carrier.py-0.0.2.dist-info/LICENSE
carrier.py-0.0.2.dist-info/METADATA
carrier.py-0.0.2.dist-info/WHEEL
carrier.py-0.0.2.dist-info/top_level.txt
carrier.py-0.0.2.dist-info/RECORD
