Metadata-Version: 2.1
Name: carrier.py
Version: 0.0.2
Summary: A package used for minor annoyances that I experience throught coding.
Home-page: https://github.com/Zacky2613/carrier.py
Author: Zacky2613
Author-email: author@example.com
License: UNKNOWN
Project-URL: Bug Tracker, https://github.com/Zacky2613/carrier.py/issues
Platform: UNKNOWN
Classifier: Programming Language :: Python :: 3
Classifier: License :: OSI Approved :: MIT License
Classifier: Operating System :: OS Independent
Requires-Python: >=3.6
License-File: LICENSE
